adrf_caching/__init__.py
adrf_caching/generics.py
adrf_caching/mixins.py
adrf_caching/utils.py
adrf_caching/viewsets.py
adrf_caching-0.1.1.dist-info/licenses/LICENSE
adrf_caching-0.1.1.dist-info/METADATA
adrf_caching-0.1.1.dist-info/WHEEL
adrf_caching-0.1.1.dist-info/top_level.txt
adrf_caching-0.1.1.dist-info/RECORD
