Metadata-Version: 2.4
Name: adrf-caching
Version: 0.1.1
Summary: Async caching with MD5 and OpenAPI schema generation for ADRF (Asynchronous Django Rest Framework) and Django 5.0+
Author-email: imgvoid <imgvoid@gmail.com>
Project-URL: Homepage, https://github.com/imgVOID/adrf-caching
Project-URL: Bug Tracker, https://github.com/imgVOID/adrf-caching/issues
Classifier: Programming Language :: Python :: 3
Classifier: License :: OSI Approved :: Apache Software License
Classifier: Operating System :: OS Independent
Classifier: Framework :: Django
Classifier: Intended Audience :: Developers
Requires-Python: >=3.10
License-File: LICENSE
Requires-Dist: Django>=5.0
Requires-Dist: djangorestframework>=3.14
Requires-Dist: asgiref>=3.5
Requires-Dist: adrf
Dynamic: license-file
